VaSeBuilder/__init__.py
VaSeBuilder/__main__.py
VaSeBuilder/argparser_beta.py
VaSeBuilder/compound_context.py
VaSeBuilder/inclusion_filter.py
VaSeBuilder/overlap_context.py
VaSeBuilder/read_id_object.py
VaSeBuilder/sample_mapper.py
VaSeBuilder/super_context.py
VaSeBuilder/variant_context.py
VaSeBuilder/variant_context_file.py
VaSeBuilder/vasebuilder.py
VaSeUtils/AcceptorReadInfo.py
VaSeUtils/AcceptorUnmappedInfo.py
VaSeUtils/AdReadInfo.py
VaSeUtils/CheckDonorFilesExist.py
VaSeUtils/Combine_VCF_Slices.py
VaSeUtils/CompareAcceptor.py
VaSeUtils/CompareAcceptorContexts.py
VaSeUtils/CompareDonorContexts.py
VaSeUtils/CompareMappingPositions.py
VaSeUtils/CompareVarcon.py
VaSeUtils/CompareVarconStats.py
VaSeUtils/CryptKeeper.py
VaSeUtils/DonorReadInfo.py
VaSeUtils/DonorUnmappedInfo.py
VaSeUtils/LogInfo.py
VaSeUtils/MVL_Parser.py
VaSeUtils/MergeVarcons.py
VaSeUtils/SubsetVariantContextFile.py
VaSeUtils/SubsetVcfByVariantContext.py
VaSeUtils/TestUtilParamCheck.py
VaSeUtils/TestVaSeUtilHelper.py
VaSeUtils/TestVaSeUtilRunner.py
VaSeUtils/UnmappedMateInfo.py
VaSeUtils/UtilParamCheck.py
VaSeUtils/VaSeCompareDonorReads.py
VaSeUtils/VaSeCompareVariantContext.py
VaSeUtils/VaSeUtilHelper.py
VaSeUtils/VaSeUtilRunner.py
VaSeUtils/VaSeUtils.py
VaSeUtils/VarconStats.py
VaSeUtils/VarconStatsFile.py
VaSeUtils/VarconVcfData.py
VaSeUtils/VariantContext.py
VaSeUtils/VariantContextFile.py
VaSeUtils/VcfVariantsInVariantContexts.py
VaSeUtils/Ygor.py
VaSeUtils/__init__.py
VaSeUtils/acceptorcheck.py
VaSeUtils/checkVaseFastQ.py
VaSeUtils/combine_varcons.py
VaSeUtils/def_getVarconVcfData.py
VaSeUtils/donorcheck.py
VaSeBuilder-20.7.1.dist-info/LICENSE
VaSeBuilder-20.7.1.dist-info/METADATA
VaSeBuilder-20.7.1.dist-info/WHEEL
VaSeBuilder-20.7.1.dist-info/entry_points.txt
VaSeBuilder-20.7.1.dist-info/top_level.txt
VaSeBuilder-20.7.1.dist-info/RECORD
