Metadata-Version: 2.1
Name: VaSeBuilder
Version: 20.7.1
Summary: VaSeBuilder, a bioinformatic tool for artificially combining multiple NGS samples into a single, hybrid sample.
Home-page: https://github.com/molgenis/VaSeBuilder
Author: T. Medina
Author-email: tylerdanmedina@gmail.com
License: UNKNOWN
Platform: UNKNOWN
Classifier: Programming Language :: Python :: 3
Classifier: License :: OSI Approved :: GNU Lesser General Public License v3 (LGPLv3)
Classifier: Operating System :: Unix
Requires-Python: >=3.6
Requires-Dist: numpy (>=1.18.1)
Requires-Dist: argon2-cffi (>=19.2.0)
Requires-Dist: pysam (>=0.15.0)
